CHANGELOG.md
LICENSE.md
MANIFEST.in
README.md
setup.py
examples/__init__.py
examples/example_td.py
ntfit/__init__.py
ntfit/tdist.py
ntfit.egg-info/PKG-INFO
ntfit.egg-info/SOURCES.txt
ntfit.egg-info/dependency_links.txt
ntfit.egg-info/requires.txt
ntfit.egg-info/top_level.txt
ntfit/hapi/__init__.py
ntfit/hapi/hapi_combustion.py
ntfit/hapi/tips2017.py
ntfit/spectrafit/Ebin_support.py
ntfit/spectrafit/Ebin_td.py
ntfit/spectrafit/__init__.py
ntfit/spectrafit/file_support.py
ntfit/spectrafit/td_support.py