Metadata-Version: 2.1
Name: ntfit
Version: 2.1.0
Summary: nonuniform-temperature fitting
Home-page: https://gitlab.com/nam5312/ntfit
Author: Nathan Malarich
Author-email: nathan.malarich@colorado.edu
License: UNKNOWN
Platform: UNKNOWN
Classifier: Development Status :: 1 - Planning
Classifier: Intended Audience :: Science/Research
Classifier: License :: OSI Approved :: BSD License
Classifier: Operating System :: Microsoft :: Windows :: Windows 10
Classifier: Programming Language :: Python :: 3.6
